practicedatasets/Covid.py
practicedatasets/__init__.py
practicedatasets/data/WPP2019_TotalPopulationBySex.csv
practicedatasets/data/covid_19_clean_complete.csv
practicedatasets-0.11.dist-info/METADATA
practicedatasets-0.11.dist-info/WHEEL
practicedatasets-0.11.dist-info/top_level.txt
practicedatasets-0.11.dist-info/RECORD
