Metadata-Version: 2.1
Name: practicedatasets
Version: 0.11
Summary: Practice Dataset
Home-page: https://github.com/mehtarjt/practicedatasets
Author: Rajat Mehta
Author-email: mehtarjt@gmail.com
License: MIT
Platform: UNKNOWN
